{
  "document": {
    "metadata": {
      "uuid": "123456789-0abc-050-1000-6102soterced",
      "document-content-type": "legislacion",
      "timestamp": 1475244493650,
      "operation": "ADD",
      "target-document-repository-id": "infojus",
      "target-index-id": "index",
      "target-document-indexing-id": "legislacion",
      "document-recovery-strategy": "abstract-legislacion",
      "friendly-url": {
        "subdomain": "decreto",
        "description": "1050-nacional-orbita-funcionamiento-registro-nacional-productores-software-servicios-informaticos-dn20160001050-2016-09-29"
      }
    },
    "content": {
      "mecanografico": 20160001050,
      "jurisdiccion": {
        "codigo": "C",
        "descripcion": "Nacional",
        "capital": "Capital Federal",
        "id-pais": 11
      },
      "numero-norma": 1050,
      "timestamp": "2016-09-30T10:44:53",
      "timestamp-alta": "2016-09-30T10:44:53",
      "timestamp-m": "2016-09-30T10:44:53",
      "tipo-norma": {
        "codigo": "DEC",
        "texto": "Decreto"
      },
      "fecha": "2016-09-29",
      "standard-normativo": "DEC C 001050 2016 09 29",
      "titulo-norma": "Órbita de Funcionamiento del Registro Nacional de Productores de Software y Servicios Informáticos",
      "publicacion-codificada": {
        "publicacion-decodificada": {
          "organismo": "Boletín Oficial",
          "fecha": "2016 09 30"
        }
      },
      "lugar-emision": "BUENOS AIRES",
      "nombre-coloquial": "DECRETO NACIONAL 1.050/2016",
      "analista": "Rocca, Adriana",
      "estado": "Vigente, de alcance general",
      "fecha-alta": "2016-09-30",
      "fecha-mod": "2016-09-30",
      "responsable": "Rocca, Adriana",
      "uid-alta": "ABM",
      "uid-mod": "ABM",
      "generalidades": {
        "sintesis": "Se establece la Órbita de Funcionamiento del Registro Nacional de Productores de Software y Servicios Informáticos",
        "observaciones-generales": "CANTIDAD DE ARTICULOS QUE COMPONEN LA NORMA: 3 NRO. DE ART. QUE ESTABLECE LA ENTRADA EN VIGENCIA: 2"
      },
      "descriptores": {
        "descriptor": [
          {
            "elegido": {
              "termino": "software"
            },
            "preferido": {
              "termino": "Derecho informático/tecnología de la información/software"
            },
            "sinonimos": {
              "termino": [
                "tecnología de la información y las comunicaciones",
                "TIC",
                "informática",
                "programa de computación"
              ]
            }
          },
          {
            "elegido": {
              "termino": "Ministerio de Producción"
            },
            "preferido": {
              "termino": "Ministerio de la Producción"
            },
            "sinonimos": {
              "termino": "Ministerio de Producción"
            }
          },
          {
            "elegido": {
              "termino": "Registro nacional de productores de software y servicios informáticos"
            },
            "preferido": {
              "termino": "Economía y finanzas/política económica/política productiva/regímenes de promoción/promoción industrial/promoción de la industria del software/Registro nacional de productores de software y servicios informáticos"
            },
            "sinonimos": {
              "termino": [
                "Hacienda y Finanzas",
                "proyectos industriales",
                "derecho económico financiero",
                "fomento industrial",
                "derecho financiero",
                "ley de promoción de la industria del software"
              ]
            }
          }
        ],
        "suggest": {
          "termino": [
            "fomento industrial (promoción industrial)",
            "programa de computación (software)",
            "tecnología de la información y las comunicaciones (tecnología de la información)",
            "derecho financiero (Economía y finanzas)",
            "derecho económico financiero (Economía y finanzas)",
            "informática (tecnología de la información)",
            "regímenes de promoción",
            "Ministerio de la Producción",
            "proyectos industriales (promoción industrial)",
            "Registro nacional de productores de software y servicios informáticos",
            "Derecho informático",
            "promoción industrial",
            "software",
            "política económica",
            "Ministerio de Producción (Ministerio de la Producción)",
            "Hacienda y Finanzas (Economía y finanzas)",
            "TIC (tecnología de la información)",
            "promoción de la industria del software",
            "tecnología de la información",
            "ley de promoción de la industria del software (promoción de la industria del software)",
            "política productiva",
            "Economía y finanzas"
          ]
        }
      },
      "visto": {
        "texto": "el Expediente Nº S01:0169524/2016 del Registro del MINISTERIO DE PRODUCCIÓN, y"
      },
      "considerando": {
        "referencias-normativas": {
          "referencia-normativa": [
            {
              "cr": null,
              "id": "REFERENCIAS_NORMATIVAS_0",
              "ref": "LEY C 025922 2004 08 18 0000 000 0000 000"
            },
            {
              "cr": null,
              "id": "REFERENCIAS_NORMATIVAS_1",
              "ref": "LEY C 026692 2011 07 27 0000 000 0000 000"
            },
            {
              "cr": null,
              "id": "REFERENCIAS_NORMATIVAS_2",
              "ref": "LEY C 025922 2004 08 18 0021 000 0000 000"
            },
            {
              "cr": null,
              "id": "REFERENCIAS_NORMATIVAS_3",
              "ref": "DEC C 001315 2013 09 09 0000 000 0000 000"
            },
            {
              "cr": null,
              "id": "REFERENCIAS_NORMATIVAS_4",
              "ref": "DEC C 000357 2002 02 21 0000 000 0000 000"
            },
            {
              "cr": null,
              "id": "REFERENCIAS_NORMATIVAS_5",
              "ref": "CON C 000000 1994 08 22 0099 000 0000 000"
            }
          ]
        },
        "sancion": "EL PRESIDENTE DE LA NACIÓN ARGENTINA DECRETA:",
        "texto": "Que mediante la Ley Nº 25.922 se creó el Régimen de Promoción de la Industria del Software, que prevé beneficios para aquellas personas jurídicas cuya actividad principal sea la industria del software y de servicios informáticos.\n\nQue por la Ley Nº 26.692 se prorrogó el Régimen mencionado, hasta el día 31 de diciembre de 2019 e implementó modificaciones a los efectos de mejorar su funcionamiento.\n\nQue por el Artículo 21 de la Ley N° 25.922 se estableció que la Autoridad de Aplicación del citado Régimen era la ex SECRETARÍA DE INDUSTRIA, COMERCIO Y DE LA PEQUEÑA Y MEDIANA EMPRESA del entonces MINISTERIO DE ECONOMÍA Y PRODUCCIÓN, actual SECRETARÍA DE INDUSTRIA Y SERVICIOS del MINISTERIO DE PRODUCCIÓN.\n\nQue, posteriormente, por medio del Decreto N° 1.315 de fecha 9 de septiembre de 2013 se creó en el ámbito de la SUBSECRETARÍA DE INDUSTRIA, dependiente de la ex SECRETARÍA DE INDUSTRIA del entonces MINISTERIO DE INDUSTRIA, el REGISTRO NACIONAL DE PRODUCTORES DE SOFTWARE Y SERVICIOS INFORMÁTICOS de las Leyes Nros. 25.922 y su modificatoria 26.692.\n\nQue mediante el Decreto Nº 357 de fecha 21 de febrero de 2002, sus modificatorios y complementarios, se establece el Organigrama de Aplicación de la Administración Nacional centralizada hasta nivel de Subsecretaría y los objetivos de las unidades organizativas determinadas en dicho organigrama, entre los cuales se encuentran los objetivos correspondientes al MINISTERIO DE PRODUCCIÓN, creándose la SUBSECRETARÍA DE SERVICIOS TECNOLÓGICOS Y PRODUCTIVOS dependiente de la SECRETARÍA DE INDUSTRIA Y SERVICIOS de dicho Ministerio.\n\nQue la citada Subsecretaría tiene entre sus objetivos intervenir en la definición de las políticas sectoriales para desarrollar los servicios tecnológicos y productivos, y utilización de los instrumentos para contribuir a promover el desarrollo y crecimiento de los mismos, entre los que se encuentra comprendido el Régimen de Promoción de la Industria del Software.\n\nQue en virtud de lo expuesto, corresponde establecer que el REGISTRO NACIONAL DE PRODUCTORES DE SOFTWARE Y SERVICIOS INFORMÁTICOS de las Leyes Nros. 25.922 y su modificatoria 26.692, creado por el Artículo 2º del Decreto Nº 1.315/13 funcionará en el ámbito de la SUBSECRETARÍA DE SERVICIOS TECNOLÓGICOS Y PRODUCTIVOS.\n\nQue la Dirección General de Asuntos Jurídicos del MINISTERIO DE PRODUCCIÓN ha tomado la intervención que le compete.\n\nQue la presente medida se dicta en ejercicio de las facultades conferidas por el Artículo 99, inciso 1 de la CONSTITUCIÓN NACIONAL. Por ello,"
      },
      "articulo": [
        {
          "referencias-normativas": {
            "referencia-normativa": [
              {
                "cr": null,
                "id": "REFERENCIAS_NORMATIVAS_0",
                "ref": "LEY C 025922 2004 08 18 0000 000 0000 000"
              },
              {
                "cr": null,
                "id": "REFERENCIAS_NORMATIVAS_1",
                "ref": "LEY C 026692 2011 07 27 0000 000 0000 000"
              }
            ]
          },
          "observa-a": {
            "referencia-normativa": {
              "cr": null,
              "id": "OBSERVA_A_0",
              "ref": "DEC C 001315 2013 09 09 0002 000 0000 000"
            }
          },
          "numero-articulo": 1,
          "texto": "ARTÍCULO 1° - Establécese que el REGISTRO NACIONAL DE PRODUCTORES DE SOFTWARE Y SERVICIOS INFORMÁTICOS de las Leyes Nros. 25.922 y su modificatoria 26.692, creado por el Artículo 2º del Decreto Nº 1.315 de fecha 9 de septiembre de 2013 funcionará en el ámbito de la SUBSECRETARÍA DE SERVICIOS TECNOLÓGICOS Y PRODUCTIVOS, dependiente de la SECRETARÍA DE INDUSTRIA Y SERVICIOS del MINISTERIO DE PRODUCCIÓN."
        },
        {
          "numero-articulo": 2,
          "texto": "ARTÍCULO 2° - El presente decreto entrará en vigencia a partir del día de su publicación en el Boletín Oficial."
        },
        {
          "numero-articulo": 3,
          "texto": "ARTÍCULO 3° - Comuníquese, publíquese, dése a la DIRECCIÓN NACIONAL DEL REGISTRO OFICIAL y archívese."
        }
      ],
      "firmantes": {
        "firmantes": "MACRI-Peña-Cabrera"
      },
      "id-infojus": "DN20160001050"
    }
  }
}