{
  "document": {
    "metadata": {
      "uuid": "123456789-0abc-405-0000-1102soterced",
      "document-content-type": "legislacion",
      "timestamp": 1410991248052,
      "operation": "ADD",
      "target-document-repository-id": "infojus",
      "target-index-id": "index",
      "target-document-indexing-id": "legislacion",
      "document-recovery-strategy": "abstract-legislacion",
      "friendly-url": {
        "subdomain": "decreto",
        "description": "504-nacional-traslado-funcionario-dn20110000504-2011-04-27"
      }
    },
    "content": {
      "mecanografico": 20110000504,
      "jurisdiccion": {
        "codigo": "C",
        "descripcion": "Nacional",
        "capital": "Capital Federal",
        "id-pais": 11
      },
      "numero-norma": 504,
      "tipo-norma": {
        "codigo": "DEC",
        "texto": "Decreto"
      },
      "fecha": "2011-04-27",
      "standard-normativo": "DEC C 000504 2011 04 27",
      "titulo-norma": "TRASLADO DE UN FUNCIONARIO.",
      "publicacion-codificada": {
        "publicacion-decodificada": {
          "organismo": "Boletín Oficial",
          "fecha": "2011 05 03"
        }
      },
      "lugar-emision": "BUENOS AIRES",
      "nombre-coloquial": "DECRETO NACIONAL 504/2011",
      "estado": "Individual, Solo Modificatoria o Sin Eficacia",
      "fecha-alta": "2011-05-03",
      "fecha-mod": "2011-05-23",
      "uid-alta": "ABM",
      "uid-mod": "ABM",
      "generalidades": {
        "sintesis": "SE TRASLADA A UN FUNCIONARIO.",
        "observaciones-generales": "CANTIDAD DE ARTICULOS QUE COMPONEN LA NORMA: 3"
      },
      "descriptores": {
        "descriptor": [
          {
            "elegido": {
              "termino": "Ministerio de Relaciones Exteriores, Comercio Internacional y Culto"
            },
            "preferido": {
              "termino": "Ministerio de Relaciones Exteriores"
            },
            "sinonimos": {
              "termino": [
                "Ministerio de Relaciones Exteriores, Comercio Internacional y Culto",
                "Ministerio de Relaciones Exteriores y Culto"
              ]
            }
          },
          {
            "elegido": {
              "termino": "embajadores extraordinarios y plenipotenciarios"
            },
            "preferido": {
              "termino": "Derecho internacional/derecho internacional público/relaciones diplomáticas/servicio exterior de la Nación/funcionarios del Servicio Exterior de la Nación/agentes diplomáticos y consulares/agentes diplomáticos/embajadas/embajadores"
            },
            "sinonimos": {
              "termino": [
                "empleados del Servicio Exterior de la Nación",
                "relaciones exteriores",
                "representaciones diplomáticas",
                "embajadores extraordinarios",
                "embajadores extraordinarios y plenipotenciarios",
                "diplomáticos"
              ]
            }
          },
          {
            "elegido": {
              "termino": "traslado del personal"
            },
            "preferido": {
              "termino": "Derecho laboral/contrato de trabajo/transferencia del contrato de trabajo/transferencia del personal"
            },
            "sinonimos": {
              "termino": [
                "contrato laboral",
                "derecho del trabajo",
                "traslado del personal",
                "cesión del personal",
                "personal transferido",
                "cesión del contrato de trabajo"
              ]
            }
          },
          {
            "elegido": {
              "termino": "funcionarios públicos"
            },
            "preferido": {
              "termino": "Derecho administrativo/Administración Pública/empleo público/agentes de la administración pública/funcionarios públicos"
            },
            "sinonimos": {
              "termino": [
                "personal del sector público",
                "relación de empleo público",
                "personal del Estado",
                "agentes de la Administración",
                "agentes públicos",
                "funcionarios y empleados públicos",
                "función pública"
              ]
            }
          },
          {
            "elegido": {
              "termino": "Jamaica"
            },
            "preferido": {
              "termino": "Jamaica"
            },
            "sinonimos": null
          }
        ],
        "suggest": {
          "termino": [
            "Derecho internacional",
            "funcionarios del Servicio Exterior de la Nación",
            "Ministerio de Relaciones Exteriores",
            "traslado del personal (transferencia del personal)",
            "diplomáticos (agentes diplomáticos)",
            "Ministerio de Relaciones Exteriores, Comercio Internacional y Culto (Ministerio de Relaciones Exteriores)",
            "agentes de la administración pública",
            "embajadores extraordinarios y plenipotenciarios (embajadores)",
            "relaciones exteriores (relaciones diplomáticas)",
            "relaciones diplomáticas",
            "agentes de la Administración (agentes de la administración pública)",
            "funcionarios públicos",
            "contrato laboral (contrato de trabajo)",
            "personal del sector público (agentes de la administración pública)",
            "empleados del Servicio Exterior de la Nación (funcionarios del Servicio Exterior de la Nación)",
            "personal transferido (transferencia del personal)",
            "servicio exterior de la Nación",
            "personal del Estado (agentes de la administración pública)",
            "relación de empleo público (empleo público)",
            "funcionarios y empleados públicos (agentes de la administración pública)",
            "agentes diplomáticos",
            "Derecho administrativo",
            "embajadores",
            "representaciones diplomáticas (embajadas)",
            "transferencia del contrato de trabajo",
            "función pública (Administración Pública)",
            "Ministerio de Relaciones Exteriores y Culto (Ministerio de Relaciones Exteriores)",
            "Jamaica",
            "embajadas",
            "Administración Pública",
            "agentes diplomáticos y consulares",
            "derecho del trabajo (Derecho laboral)",
            "contrato de trabajo",
            "agentes públicos (agentes de la administración pública)",
            "cesión del contrato de trabajo (transferencia del contrato de trabajo)",
            "derecho internacional público",
            "transferencia del personal",
            "Derecho laboral",
            "empleo público",
            "embajadores extraordinarios (embajadores)",
            "cesión del personal (transferencia del personal)"
          ]
        }
      },
      "visto": {
        "referencias-normativas": {
          "referencia-normativa": {
            "cr": null,
            "id": "REFERENCIAS_NORMATIVAS_0",
            "ref": "DEC C 000152 2006 02 09 0000 000 0000 000"
          }
        },
        "texto": "el Expediente Nº 61.254/2010 del Registro del MINISTERIO DE RELACIONES EXTERIORES, COMERCIO INTERNACIONAL Y CULTO, el Decreto Nº 152 de fecha 9 de febrero de 2006, y"
      },
      "considerando": {
        "referencias-normativas": {
          "referencia-normativa": {
            "cr": null,
            "id": "REFERENCIAS_NORMATIVAS_0",
            "ref": "CON C 000000 1994 08 22 0099 000 0000 000"
          }
        },
        "sancion": "LA PRESIDENTA DE LA NACION ARGENTINA            DECRETA:",
        "texto": "Que por el Decreto mencionado en el Visto se designó Embajador Extraordinario y Plenipotenciario de la República en JAMAICA al señor Ministro Plenipotenciario de Segunda Clase D. Mario José PINO.\n\nQue por el Expediente citado en el Visto y atento a razones de servicio, resulta necesario disponer el traslado a la República del señor funcionario citado anteriormente.\n\nQue la SUBSECRETARIA LEGAL, TECNICA Y ADMINISTRATIVA, la SECRETARIA DE COORDINACION Y COOPERACION INTERNACIONAL, la SECRETARIA DE COMERCIO Y RELACIONES ECONOMICAS INTERNACIONALES y la SECRETARIA DE RELACIONES EXTERIORES del MINISTERIO DE RELACIONES EXTERIORES, COMERCIO INTERNACIONAL Y CULTO han tomado debida intervención, en el ámbito de sus respectivas competencias.\n\nQue el presente Decreto se dicta en uso de las facultades conferidas por el Artículo 99, inciso 7 de la CONSTITUCION NACIONAL.\n\nPor ello,"
      },
      "articulo": [
        {
          "numero-articulo": 1,
          "texto": "Artículo 1º - Trasládase de la Embajada de la República en JAMAICA al MINISTERIO DE RELACIONES EXTERIORES, COMERCIO INTERNACIONAL Y CULTO al señor Ministro Plenipotenciario de Segunda Clase D. Mario José PINO (M.I. Nº 8.653.535)."
        },
        {
          "numero-articulo": 2,
          "texto": "Art. 2º - Los gastos que demande el cumplimiento del presente Decreto se imputarán a las respectivas partidas del presupuesto del MINISTERIO DE RELACIONES EXTERIORES, COMERCIO INTERNACIONAL Y CULTO para el presente ejercicio."
        },
        {
          "numero-articulo": 3,
          "texto": "Art. 3º - Comuníquese, publíquese, dése a la Dirección Nacional del Registro Oficial y archívese."
        }
      ],
      "firmantes": {
        "firmantes": "FERNANDEZ DE KIRCHNER-Timerman"
      },
      "id-infojus": "DN20110000504"
    }
  }
}