{
  "document": {
    "metadata": {
      "uuid": "123456789-0abc-027-1000-3102soterced",
      "document-content-type": "legislacion",
      "timestamp": 1410991599136,
      "operation": "ADD",
      "target-document-repository-id": "infojus",
      "target-index-id": "index",
      "target-document-indexing-id": "legislacion",
      "document-recovery-strategy": "abstract-legislacion",
      "friendly-url": {
        "subdomain": "decreto",
        "description": "1720-nacional-reconocimiento-exarca-apostlico-para-fieles-rito-greco-melquita-jurisdiccin-todo-territorio-pas-dn20130001720-2013-10-31"
      }
    },
    "content": {
      "mecanografico": 20130001720,
      "jurisdiccion": {
        "codigo": "C",
        "descripcion": "Nacional",
        "capital": "Capital Federal",
        "id-pais": 11
      },
      "numero-norma": 1720,
      "timestamp": "2013-11-12T12:35:45",
      "timestamp-alta": "2013-11-12T12:35:45",
      "timestamp-m": "2013-11-12T12:35:45",
      "tipo-norma": {
        "codigo": "DEC",
        "texto": "Decreto"
      },
      "fecha": "2013-10-31",
      "standard-normativo": "DEC C 001720 2013 10 31",
      "titulo-norma": "Reconocimiento del Exarca Apostólico para los fieles de rito greco-melquita con jurisdicción en todo el territorio del país",
      "publicacion-codificada": {
        "publicacion-decodificada": {
          "organismo": "Boletín Oficial",
          "fecha": "2013 11 12"
        }
      },
      "lugar-emision": "BUENOS AIRES",
      "nombre-coloquial": "DECRETO NACIONAL 1.720/2013",
      "estado": "Individual, Solo Modificatoria o Sin Eficacia",
      "fecha-alta": "2013-11-12",
      "fecha-mod": "2013-11-12",
      "uid-alta": "ABM",
      "uid-mod": "ABM",
      "generalidades": {
        "sintesis": "Se reconoce al Exarca Apostólico para los fieles de rito greco-melquita con jurisdicción en todo el territorio del país.",
        "observaciones-generales": "CANTIDAD DE ARTICULOS QUE COMPONEN LA NORMA:  2"
      },
      "descriptores": {
        "descriptor": [
          {
            "elegido": {
              "termino": "Iglesia Católica"
            },
            "preferido": {
              "termino": "Derecho civil/personas jurídicas/personas jurídicas de carácter público/Iglesia Católica"
            },
            "sinonimos": {
              "termino": "personas de existencia ideal"
            }
          },
          {
            "elegido": {
              "termino": "obispos"
            },
            "preferido": {
              "termino": "Derecho civil/personas jurídicas/personas jurídicas de carácter público/Iglesia Católica/diócesis/obispos"
            },
            "sinonimos": {
              "termino": "personas de existencia ideal"
            }
          },
          {
            "elegido": {
              "termino": "congregaciones religiosas"
            },
            "preferido": {
              "termino": "Derecho civil/personas jurídicas/personas jurídicas de carácter público/Iglesia Católica/congregaciones religiosas"
            },
            "sinonimos": {
              "termino": [
                "órdenes religiosas",
                "personas de existencia ideal"
              ]
            }
          },
          {
            "elegido": {
              "termino": "rito greco melquita"
            },
            "preferido": {
              "termino": "Derecho civil/personas jurídicas/personas jurídicas de carácter público/Iglesia Católica/exarcado/rito greco melquita"
            },
            "sinonimos": {
              "termino": "personas de existencia ideal"
            }
          }
        ],
        "suggest": {
          "termino": [
            "exarcado",
            "rito greco melquita",
            "personas de existencia ideal (personas jurídicas)",
            "Iglesia Católica",
            "congregaciones religiosas",
            "diócesis",
            "órdenes religiosas (congregaciones religiosas)",
            "personas jurídicas",
            "obispos",
            "Derecho civil",
            "personas jurídicas de carácter público"
          ]
        }
      },
      "visto": {
        "texto": "el Expediente Nº 32.353/2013 del Registro del MINISTERIO DE RELACIONES EXTERIORES Y CULTO, y"
      },
      "considerando": {
        "referencias-normativas": {
          "referencia-normativa": {
            "cr": null,
            "id": "REFERENCIAS_NORMATIVAS_0",
            "ref": "TRA C 017032 1966 11 23 0000 000 0000 000"
          }
        },
        "sancion": "EL VICEPRESIDENTE DE LA NACION ARGENTINA EN EJERCICIO DEL PODER EJECUTIVO DECRETA:",
        "texto": "Que por nota de la Nunciatura Apostólica se comunica que Su Santidad FRANCISCO designó Exarca Apostólico del Exarcado para los fieles de rito greco-melquita con jurisdicción en todo el territorio del país al Reverendo Padre Ibrahim SALAMEH.\n\nQue se trata de la designación de Obispo Titular con funciones de Exarca.\n\nQue conforme al Artículo 3° del Acuerdo firmado entre la SANTA SEDE y la REPUBLICA ARGENTINA el 10 de octubre de 1966, aprobado por Ley Nº 17.032, el nombramiento de Obispos es competencia de la SANTA SEDE.\n\nQue se han cumplido previamente los trámites previstos por la norma indicada y el Obispo designado reúne los requisitos allí establecidos.\n\nQue a los fines civiles y administrativos es necesario el reconocimiento de la designación efectuada.\n\nQue la SUBSECRETARIA LEGAL, TECNICA Y ADMINISTRATIVA, la SECRETARIA DE COORDINACION Y COOPERACION INTERNACIONAL y la SECRETARIA DE CULTO del MINISTERIO DE RELACIONES EXTERIORES Y CULTO han tomado la intervención que les compete.\n\nPor ello,"
      },
      "articulo": [
        {
          "numero-articulo": 1,
          "texto": "Artículo 1° - Reconócese al Reverendo Padre Ibrahim SALAMEH (D.N.I. Nº 18.641.632) como Exarca Apostólico del Exarcado para los fieles de rito greco-melquita con jurisdicción en todo el territorio del país desde la fecha de la toma de posesión."
        },
        {
          "numero-articulo": 2,
          "texto": "Art. 2° - Comuníquese, publíquese, dése a la Dirección Nacional del Registro Oficial y archívese."
        }
      ],
      "firmantes": {
        "firmantes": "AMADO BOUDOU-Timerman"
      },
      "id-infojus": "DN20130001720"
    }
  }
}